physiognomy/__init__.py
physiognomy/stats.py
physiognomy/utils.py
physiognomy-0.2.2.dist-info/DESCRIPTION.rst
physiognomy-0.2.2.dist-info/METADATA
physiognomy-0.2.2.dist-info/RECORD
physiognomy-0.2.2.dist-info/WHEEL
physiognomy-0.2.2.dist-info/metadata.json
physiognomy-0.2.2.dist-info/top_level.txt
