Metadata-Version: 2.0
Name: physiognomy
Version: 0.2.2
Summary: All hail god of physiognomy! Long live the pseudoscience!
Home-page: https://github.com/davidwdw/physiognomy
Author: Dawei Wang
Author-email: david.wang@kellogg.northwestern.edu
License: BSD 2-clause
Platform: UNKNOWN
Classifier: Development Status :: 1 - Planning
Classifier: Intended Audience :: Science/Research
Classifier: License :: OSI Approved :: BSD License
Classifier: Operating System :: POSIX :: Linux
Classifier: Programming Language :: Python :: 3.6
Requires-Dist: matplotlib
Requires-Dist: numpy
Requires-Dist: opencv-python-headless
Requires-Dist: pandas
Requires-Dist: python-dotenv
Requires-Dist: requests
Requires-Dist: scikit-learn
Requires-Dist: scipy
Requires-Dist: statsmodels
